metapandas/__init__.py
metapandas/auto.py
metapandas/config.py
metapandas/metadata.py
metapandas/metadataframe.py
metapandas/util.py
metapandas/hooks/geopandas.py
metapandas/hooks/manager.py
metapandas/hooks/pandas.py
metapandas-0.0.0b13.dist-info/LICENSE
metapandas-0.0.0b13.dist-info/METADATA
metapandas-0.0.0b13.dist-info/WHEEL
metapandas-0.0.0b13.dist-info/entry_points.txt
metapandas-0.0.0b13.dist-info/top_level.txt
metapandas-0.0.0b13.dist-info/RECORD
