Metadata-Version: 2.1
Name: metapandas
Version: 0.0.0b13
Summary: Augemented pandas for tracking JSON metadata
Home-page: https://github.com/LightBytes/metapandas
Author: Liam Deacon
Author-email: liam.deacon@lightbytestechnology.co.uk
License: MIT
Platform: UNKNOWN
Classifier: Development Status :: 4 - Beta
Classifier: Topic :: Utilities
Classifier: Programming Language :: Python
Classifier: Programming Language :: Python :: 3
Classifier: Programming Language :: Python :: 3 :: Only
Classifier: Programming Language :: Python :: 3.5
Classifier: Programming Language :: Python :: 3.6
Classifier: Programming Language :: Python :: 3.7
Classifier: Operating System :: POSIX :: Linux
Classifier: Operating System :: Unix
Classifier: Operating System :: MacOS
Classifier: Operating System :: Microsoft :: Windows
Classifier: Programming Language :: Python :: Implementation :: CPython
Classifier: Topic :: Software Development :: Libraries :: Python Modules
Classifier: Intended Audience :: Science/Research
Classifier: Intended Audience :: Developers
Requires-Dist: pandas (>=0.25.3)
Requires-Dist: psutil
Requires-Dist: loguru
Requires-Dist: py-cpuinfo ; platform_system != "Windows"
